zodchy/__init__.py
zodchy/py.typed
zodchy/codex/__init__.py
zodchy/codex/cqea.py
zodchy/codex/operator.py
zodchy/codex/types.py
zodchy/toolbox/__init__.py
zodchy/toolbox/di.py
zodchy/toolbox/identity.py
zodchy/toolbox/notation.py
zodchy/toolbox/processing.py
zodchy-1.1.0.dist-info/METADATA
zodchy-1.1.0.dist-info/WHEEL
zodchy-1.1.0.dist-info/RECORD
